vscodenb/__init__.py
vscodenb/cpu_monitor.py
vscodenb/plot_theme.py
vscodenb/progress.py
vscodenb/slurm_magic.py
vscodenb/utils.py
vscodenb/widget_theme.py
vscodenb-0.1.32.dist-info/licenses/LICENSE
vscodenb-0.1.32.dist-info/METADATA
vscodenb-0.1.32.dist-info/WHEEL
vscodenb-0.1.32.dist-info/top_level.txt
vscodenb-0.1.32.dist-info/RECORD
