Metadata-Version: 2.4
Name: vscodenb
Version: 0.1.32
Summary: Utilities and styling for notebooks in vscode
Author-email: Kasper Munch <kaspermunch@birc.au.dk>
License: MIT
Project-URL: Homepage, https://github.com/munch-group/vscodenb
Project-URL: Repository, https://github.com/munch-group/vscodenb
Project-URL: Documentation, https://munch-group.org/vscodenb
Classifier: License :: OSI Approved :: MIT License
Classifier: Programming Language :: Python :: 3
Requires-Python: >=3.8
License-File: LICENSE
Requires-Dist: IPython
Requires-Dist: quarto
Requires-Dist: seaborn
Requires-Dist: numpy
Requires-Dist: json5
Requires-Dist: psutil
Requires-Dist: rich
Requires-Dist: tqdm
Requires-Dist: multiprocess
Requires-Dist: jupyter
Requires-Dist: nbconvert
Dynamic: license-file
